{
  "sizes": [
    152,
    80,
    74
  ],
  "details": {
    "description": "שולחן אוכל עם\u200E 2 הארכות. מקום ל–2 - 4 סועדים; ניתן לכוונן את אורך השולחן לפי הצורך.\n6 מגירות מתחת למשטח השולחן לאחסון מפיות, סכו\"ם, נרות וכדומה.\nשולחן זה נבדק בסטנדרטים הגבוהים ביותר לחוזק, יציבות ובטיחות בכדי לעמוד בשימוש יומיומי בביתכם למשך שנים. ",
    "good_to_know": "מימדיו הקטנים של שולחן מקלים על שילובו עם הריהוט, גם כאשר המקום מוגבל."
  },
  "category": "TABLES",
  "price": 1100,
  "color": "WHITE",
  "rendable": "models/table_4.glb",
  "images": [
    "images/table_4_1.jpg",
    "images/table_4_2.jpg"
  ],
  "source": "https://www.ikea.co.il/catalogue/Dining/Tables/10423886",
  "model": "NORDEN"
}
